{
  "updated_at": "2026-04-01T06:43:33.297264+00:00",
  "trending_solana": [
    {
      "name": "SOL",
      "symbol": "SOL",
      "price_usd": "143.20",
      "price_change_24h": "-0.44",
      "volume_24h": "180404.98",
      "market_cap_usd": "3293488",
      "pool_address": "3fkdUeRvUnSKKYgTyX1hkiJmJVbiYtDwyBwxYW19n28t"
    },
    {
      "name": "SOL",
      "symbol": "SOL",
      "price_usd": "83.42",
      "price_change_24h": "-0.77",
      "volume_24h": "160564.73",
      "market_cap_usd": "1251414",
      "pool_address": "FEoaEJGjZzE5pfmvLQY8cLJJQokw2y796akvb4j4FuSw"
    },
    {
      "name": "SOL",
      "symbol": "SOL",
      "price_usd": "92.43",
      "price_change_24h": "-0.82",
      "volume_24h": "80771.99",
      "market_cap_usd": "2310801",
      "pool_address": "3dS5VZhBAmv3FH5JSz221c7nBjLMaoTwKLcLm5N7mtiC"
    },
    {
      "name": "SOL",
      "symbol": "SOL",
      "price_usd": "78.36",
      "price_change_24h": "-0.1",
      "volume_24h": "40324.6",
      "market_cap_usd": "9403843",
      "pool_address": "GhhUiNcoFKEtZ9RTGd1DgHHouDAJrW9DDADmX13jdGEY"
    },
    {
      "name": "SOL",
      "symbol": "SOL",
      "price_usd": "0.0002795",
      "price_change_24h": "-3.64",
      "volume_24h": "10402.14",
      "market_cap_usd": "229359",
      "pool_address": "CcYbXbMHr2o9Vyz2wmJcRvi59wh42xkXf6qrzChbHPN5"
    }
  ],
  "trending_base": [
    {
      "name": "cbBTC",
      "symbol": "cbBTC",
      "price_usd": "69039.24",
      "price_change_24h": "2.41",
      "volume_24h": "59803982.49",
      "market_cap_usd": "2391144030",
      "pool_address": "0x70aCDF2Ad0bf2402C957154f944c19Ef4e1cbAE1"
    },
    {
      "name": "cbBTC",
      "symbol": "cbBTC",
      "price_usd": "69033.20",
      "price_change_24h": "2.41",
      "volume_24h": "54834733.3",
      "market_cap_usd": "2390934663",
      "pool_address": "0xC211e1f853A898Bd1302385CCdE55f33a8C4B3f3"
    },
    {
      "name": "cbBTC",
      "symbol": "cbBTC",
      "price_usd": "69036.56",
      "price_change_24h": "2.42",
      "volume_24h": "22021876.7",
      "market_cap_usd": "2391051013",
      "pool_address": "0x22AEe3699b6A0fEd71490C103Bd4E5f3309891D5"
    },
    {
      "name": "cbETH",
      "symbol": "cbETH",
      "price_usd": "2417.78",
      "price_change_24h": "4.3",
      "volume_24h": "1792330.09",
      "market_cap_usd": "292649291",
      "pool_address": "0x47cA96Ea59C13F72745928887f84C9F52C3D7348"
    },
    {
      "name": "cbADA",
      "symbol": "cbADA",
      "price_usd": "0.2529",
      "price_change_24h": "3.41",
      "volume_24h": "124099.86",
      "market_cap_usd": "8769496",
      "pool_address": "0xb862F23ba38c8C65e256782B31E8C08C9aefd612"
    },
    {
      "name": "cbXRP",
      "symbol": "cbXRP",
      "price_usd": "1.36",
      "price_change_24h": "2.81",
      "volume_24h": "122657.72",
      "market_cap_usd": "70187222",
      "pool_address": "0x170b6bFc071426aaB7C81AE12383219facBb6B6A"
    },
    {
      "name": "cbXRP",
      "symbol": "cbXRP",
      "price_usd": "1.34",
      "price_change_24h": "1.51",
      "volume_24h": "107745.89",
      "market_cap_usd": "69455277",
      "pool_address": "0xA6da283cf7D06b2279626E787c329d6aCF7e2994"
    },
    {
      "name": "BENJI",
      "symbol": "BENJI",
      "price_usd": "0.001812",
      "price_change_24h": "2.98",
      "volume_24h": "53515.92",
      "market_cap_usd": "1812042",
      "pool_address": "0x16905890A1D02b6F824387419319Bf4188B961b0"
    },
    {
      "name": "cbLTC",
      "symbol": "cbLTC",
      "price_usd": "54.74",
      "price_change_24h": "1.78",
      "volume_24h": "33692.74",
      "market_cap_usd": "3390486",
      "pool_address": "0x200681425b0C8D78C6a467512C5D49FA56BaC88A"
    },
    {
      "name": "Base is for everyone",
      "symbol": "Base is for everyone",
      "price_usd": "0.0003711",
      "price_change_24h": "7.9",
      "volume_24h": "18513.58",
      "market_cap_usd": "371162",
      "pool_address": "0x06D7874037E622d6eF42294Cf32EB259806Cb1C6"
    }
  ],
  "volume_solana": [],
  "volume_base": [],
  "openclaw_tokens": [
    {
      "name": "Moltbook",
      "symbol": "MOLT",
      "price_usd": "0.00001867",
      "price_change_24h": "1.34",
      "market_cap_usd": "1867389",
      "volume_24h": "35486.11",
      "pool_address": "0x15f351bf1637b43d70631ba95fb9bbb1ff21761c29b034c1b380aecb922464dd"
    },
    {
      "name": "AntiHunter",
      "symbol": "AntiHunter",
      "price_usd": "0.000002315",
      "price_change_24h": "-2.1",
      "market_cap_usd": "230910",
      "volume_24h": "25238.38",
      "pool_address": "0x21a138687a96298d44f5dc167ba4950c16d0fa680e8663540c0845834b4aac37"
    },
    {
      "name": "CLAWNCH",
      "symbol": "CLAWNCH",
      "price_usd": "0.00003357",
      "price_change_24h": "-0.6",
      "market_cap_usd": "3342270",
      "volume_24h": "56674.59",
      "pool_address": "0x03d3c21ea1daf51dd2898ebaf9342a93374877ba6ab34cc7ffe5b5d43ee46e0a"
    },
    {
      "name": "Osobot",
      "symbol": "OSO",
      "price_usd": "0.000003574",
      "price_change_24h": "0.75",
      "market_cap_usd": "355657",
      "volume_24h": "6896.54",
      "pool_address": "0x1da0ba703f7a745b200492bbeae8d4547f144bfc15ed7ab65760049be44e2a94"
    },
    {
      "name": "BankrWallet",
      "symbol": "BNKRW",
      "price_usd": "0.000002477",
      "price_change_24h": "5.5",
      "market_cap_usd": "247772",
      "volume_24h": "889.66",
      "pool_address": "0x6c8fd04c19e3c6c3efc21f6f5ae79c1453a19d971b7b7d4969df1928c380aaad"
    },
    {
      "name": "fomolt",
      "symbol": "fomolt",
      "price_usd": "0.000001930",
      "price_change_24h": "0",
      "market_cap_usd": "193097",
      "volume_24h": "1.4",
      "pool_address": "0x3e81aac5ec50c74b3bc88a6c063bad6ff6cdc260dda96992e6c5885ee05f363f"
    },
    {
      "name": "Work402",
      "symbol": "WORK",
      "price_usd": "0.0002681",
      "price_change_24h": "-2.1",
      "market_cap_usd": "268142",
      "volume_24h": "3914.87",
      "pool_address": "0x3fEE213035fCec8cB2589f25f06197008C33641E"
    },
    {
      "name": "Squaer",
      "symbol": "Squaer",
      "price_usd": "0.0000004823",
      "price_change_24h": "-2.34",
      "market_cap_usd": "48232",
      "volume_24h": "725.07",
      "pool_address": "0x1d201b9760e79e058f3eaaddcb2cf777fbfdca39597c972b4e783acdfbf77ed6"
    },
    {
      "name": "MOLT BUNKER",
      "symbol": "BUNKER",
      "price_usd": "0.0000008218",
      "price_change_24h": "1.65",
      "market_cap_usd": "82182",
      "volume_24h": "419.86",
      "pool_address": "0x22d0b6e5b2bfa4a1bb4567114a448fe3cbfb7ba1baa79c8d974464de7e4854b3"
    },
    {
      "name": "0x0f325c",
      "symbol": "???",
      "price_usd": "0",
      "price_change_24h": "0",
      "market_cap_usd": "0",
      "volume_24h": "0",
      "pool_address": "---"
    },
    {
      "name": "0xd65579",
      "symbol": "???",
      "price_usd": "0",
      "price_change_24h": "0",
      "market_cap_usd": "0",
      "volume_24h": "0",
      "pool_address": "---"
    },
    {
      "name": "Juno Agent",
      "symbol": "JUNO",
      "price_usd": "0.000008258",
      "price_change_24h": "2.18",
      "market_cap_usd": "816613",
      "volume_24h": "57034.72",
      "pool_address": "0x1635213e2b19e459a4132df40011638b65ae7510a35d6a88c47ebf94912c7f2e"
    },
    {
      "name": "FELIX",
      "symbol": "FELIX",
      "price_usd": "0.00001037",
      "price_change_24h": "6.77",
      "market_cap_usd": "996075",
      "volume_24h": "36762.04",
      "pool_address": "0x6e19027912db90892200a2b08c514921917bc55d7291ec878aa382c193b50084"
    },
    {
      "name": "Molten",
      "symbol": "Molten",
      "price_usd": "0.000005341",
      "price_change_24h": "-7.35",
      "market_cap_usd": "499345",
      "volume_24h": "25832.39",
      "pool_address": "0x5d58fdc2eea2e365c8c476a15a61635804796fd891d9b348bbe514c0417ea070"
    },
    {
      "name": "clawd.atg.eth",
      "symbol": "CLAWD",
      "price_usd": "0.00002839",
      "price_change_24h": "-4.83",
      "market_cap_usd": "2803465",
      "volume_24h": "72749.57",
      "pool_address": "0x9fd58e73d8047cb14ac540acd141d3fc1a41fb6252d674b730faf62fe24aa8ce"
    },
    {
      "name": "Doppel",
      "symbol": "Doppel",
      "price_usd": "0.000003732",
      "price_change_24h": "-14.67",
      "market_cap_usd": "360558",
      "volume_24h": "77496.94",
      "pool_address": "0x87e22831f5b0b48759b9113128d1472a97e366ae777da0de2c990cb82d739b54"
    },
    {
      "name": "tokenbot",
      "symbol": "CLANKER",
      "price_usd": "26.28",
      "price_change_24h": "3.13",
      "market_cap_usd": "25927521",
      "volume_24h": "19599.24",
      "pool_address": "0xC1a6FBeDAe68E1472DbB91FE29B51F7a0Bd44F97"
    },
    {
      "name": "DebtReliefBot",
      "symbol": "DRB",
      "price_usd": "0.00009075",
      "price_change_24h": "21.03",
      "market_cap_usd": "8955965",
      "volume_24h": "89490.58",
      "pool_address": "0x5116773e18A9C7bB03EBB961b38678E45E238923"
    },
    {
      "name": "Lumen",
      "symbol": "Lumen",
      "price_usd": "0.000003171",
      "price_change_24h": "3.84",
      "market_cap_usd": "317124",
      "volume_24h": "770.46",
      "pool_address": "0xd96de1b974733e54940c24b4d7d4f7178da52dae8d058031b5a1da308c8bb29a"
    }
  ]
}