{
  "updated_at": "2026-03-23T06:43:10.060928+00:00",
  "cycle": "20260323_0643",
  "signals": [
    {
      "symbol": "MOLT",
      "type": "BULL_FLAG",
      "status": "CONFIRMED",
      "since": "2026-03-23",
      "note": "New bull flag detection"
    },
    {
      "symbol": "AntiHunter",
      "type": "BULL_FLAG",
      "status": "HOLDING",
      "since": "previous cycle",
      "note": "Continued bull flag detection"
    },
    {
      "symbol": "CLAWNCH",
      "type": "BULL_FLAG",
      "status": "CONFIRMED",
      "since": "2026-03-23",
      "note": "New bull flag detection"
    },
    {
      "symbol": "FELIX",
      "type": "BULL_FLAG",
      "status": "HOLDING",
      "since": "previous cycle",
      "note": "Stable bull flag detection"
    },
    {
      "symbol": "JUNO",
      "type": "BULL_FLAG",
      "status": "HOLDING",
      "since": "previous cycle",
      "note": "Ongoing bull flag detection"
    },
    {
      "symbol": "Lumen",
      "type": "PHASE_CHANGE",
      "status": "CONFIRMED",
      "since": "2026-03-23",
      "note": "Phase change to accumulation and new bull flag"
    },
    {
      "symbol": "CLANKER",
      "type": "ACCUMULATION",
      "status": "HOLDING",
      "since": "previous cycle",
      "note": "Continued accumulation phase"
    },
    {
      "symbol": "DRB",
      "type": "CONSOLIDATION",
      "status": "HOLDING",
      "since": "previous cycle",
      "note": "Ongoing consolidation phase"
    },
    {
      "symbol": "VVV",
      "type": "ACCUMULATION",
      "status": "WEAKENING",
      "since": "previous cycle",
      "note": "Continued accumulation with weakening signal"
    }
  ],
  "evolution_report": "### 1. MARKET OVERVIEW\nThe overall market is currently in a mixed state, with most tokens in distribution, but some showing signs of accumulation. Notable shifts include Lumen's phase change from consolidation to accumulation, accompanied by a significant increase in its bull flag probability and a substantial positive change in its net buying pressure (NBP).\n\n### 2. PRICE & VOLUME HIGHLIGHTS\nNone of the tokens have shown significant price movements (all at 0% change), and there are no notable volume highlights as all volume deltas are at 0%. However, Lumen stands out with a significant increase in its NBP delta (+23.2) and a substantial bull flag probability increase, indicating potential bullish activity.\n\n### 3. SIGNAL TRACKING\n- **MOLT**: The bull flag detected is a new signal, indicating potential for a price increase. Status: CONFIRMED.\n- **AntiHunter**: Despite a slight decrease in FHS, the bull flag remains detected, but with less conviction. Status: HOLDING.\n- **CLAWNCH**: A new bull flag detection with a significant decrease in FHS and an increase in NBP, suggesting potential upside. Status: CONFIRMED.\n- **FELIX**: The bull flag remains detected with minimal changes, indicating a continued but stable potential for price increase. Status: HOLDING.\n- **JUNO**: The bull flag detection continues with minor changes, suggesting ongoing potential. Status: HOLDING.\n- **Lumen**: With its phase change to accumulation and a new bull flag detection, Lumen's signal is strengthening. Status: CONFIRMED.\n- **CLANKER**: The accumulation phase continues with minimal changes, indicating a stable but less active signal. Status: HOLDING.\n- **DRB**: The consolidation phase continues with no significant changes, keeping the signal stable. Status: HOLDING.\n- **VVV**: Accumulation continues with minimal changes, suggesting a stable but potentially weakening signal. Status: WEAKENING.\n\n### 4. NEW SIGNALS DETECTED\n- **Lumen**'s phase change to accumulation and new bull flag detection are significant new signals.\n- **MOLT** and **CLAWNCH** have new bull flag detections, indicating potential price increases.\n\n### 5. SIGNAL WATCHLIST (JSON)\n```json\n[\n  {\"symbol\": \"MOLT\", \"type\": \"BULL_FLAG\", \"status\": \"CONFIRMED\", \"since\": \"2026-03-23\", \"note\": \"New bull flag detection\"},\n  {\"symbol\": \"AntiHunter\", \"type\": \"BULL_FLAG\", \"status\": \"HOLDING\", \"since\": \"previous cycle\", \"note\": \"Continued bull flag detection\"},\n  {\"symbol\": \"CLAWNCH\", \"type\": \"BULL_FLAG\", \"status\": \"CONFIRMED\", \"since\": \"2026-03-23\", \"note\": \"New bull flag detection\"},\n  {\"symbol\": \"FELIX\", \"type\": \"BULL_FLAG\", \"status\": \"HOLDING\", \"since\": \"previous cycle\", \"note\": \"Stable bull flag detection\"},\n  {\"symbol\": \"JUNO\", \"type\": \"BULL_FLAG\", \"status\": \"HOLDING\", \"since\": \"previous cycle\", \"note\": \"Ongoing bull flag detection\"},\n  {\"symbol\": \"Lumen\", \"type\": \"PHASE_CHANGE\", \"status\": \"CONFIRMED\", \"since\": \"2026-03-23\", \"note\": \"Phase change to accumulation and new bull flag\"},\n  {\"symbol\": \"CLANKER\", \"type\": \"ACCUMULATION\", \"status\": \"HOLDING\", \"since\": \"previous cycle\", \"note\": \"Continued accumulation phase\"},\n  {\"symbol\": \"DRB\", \"type\": \"CONSOLIDATION\", \"status\": \"HOLDING\", \"since\": \"previous cycle\", \"note\": \"Ongoing consolidation phase\"},\n  {\"symbol\": \"VVV\", \"type\": \"ACCUMULATION\", \"status\": \"WEAKENING\", \"since\": \"previous cycle\", \"note\": \"Continued accumulation with weakening signal\"}\n]\n```\n\n### 6. KEY INSIGHT\nThe most significant development across the watchlist is Lumen's phase change to accumulation, accompanied by a new bull flag detection, indicating a strong potential for a price increase."
}