{
  "updated_at": "2026-03-26T04:43:02.168289+00:00",
  "synthesis_table": [
    {
      "symbol": "MOLT",
      "address": "0xB695559b26BB2c9703ef1935c37AeaE9526bab07",
      "fhs": 7.1,
      "ces": 0,
      "phase": "DISTRIBUTION",
      "nbp": -46.31901840490797,
      "bpi": 0.0,
      "price_usd": 2.19e-05,
      "change_24h": -7.81,
      "volume_24h": 90126.0
    },
    {
      "symbol": "AntiHunter",
      "address": "0xe2f3FaE4bc62E21826018364aa30ae45D430bb07",
      "fhs": 6.2,
      "ces": 0,
      "phase": "DISTRIBUTION",
      "nbp": -48.97959183673469,
      "bpi": 0.030395505575449278,
      "price_usd": 3.061e-06,
      "change_24h": -2.84,
      "volume_24h": 8157.64
    },
    {
      "symbol": "CLAWNCH",
      "address": "0xa1F72459dfA10BAD200Ac160eCd78C6b77a747be",
      "fhs": 6.6,
      "ces": 0,
      "phase": "DISTRIBUTION",
      "nbp": -56.49999999999999,
      "bpi": 0.0,
      "price_usd": 3.486e-05,
      "change_24h": -3.12,
      "volume_24h": 85201.53
    },
    {
      "symbol": "BNKRW",
      "address": "0xf48bC234855aB08ab2EC0cfaaEb2A80D065a3b07",
      "fhs": 4.5,
      "ces": 0,
      "phase": "DISTRIBUTION",
      "nbp": -33.33333333333333,
      "bpi": 0.0223553353792385,
      "price_usd": 2.354e-06,
      "change_24h": -0.3,
      "volume_24h": 612.47
    },
    {
      "symbol": "fomolt",
      "address": "0xeff5672a3e73e104A56b7d16c1166f2Ae0714b07",
      "fhs": 5.9,
      "ces": 0,
      "phase": "DISTRIBUTION",
      "nbp": -46.15384615384615,
      "bpi": 0.0,
      "price_usd": 2.067e-06,
      "change_24h": -0.71,
      "volume_24h": 137.61
    },
    {
      "symbol": "WORK",
      "address": "0xe6725BE5AC8DFf03538a9ef3E3a7A6BEd256bB4f",
      "fhs": 6.0,
      "ces": 0,
      "phase": "DISTRIBUTION",
      "nbp": -44.0,
      "bpi": 0.0,
      "price_usd": 0.000312,
      "change_24h": -27.56,
      "volume_24h": 8364.41
    },
    {
      "symbol": "Squaer",
      "address": "0x2A767b649A4c469f2c4F88f85D4eFb6be7abFB07",
      "fhs": 6.4,
      "ces": 0,
      "phase": "DISTRIBUTION",
      "nbp": -75.0,
      "bpi": 0.0,
      "price_usd": 5.526e-07,
      "change_24h": 1.11,
      "volume_24h": 133.9
    },
    {
      "symbol": "BUNKER",
      "address": "0xCe16Ef461d88256D2D80DFD31F0D9E7a9fD59213",
      "fhs": 5.6,
      "ces": 0,
      "phase": "DISTRIBUTION",
      "nbp": -80.0,
      "bpi": 0.044793735216914266,
      "price_usd": 9.067e-07,
      "change_24h": -0.09,
      "volume_24h": 334.28
    },
    {
      "symbol": "FELIX",
      "address": "0xf30Bf00edd0C22db54C9274B90D2A4C21FC09b07",
      "fhs": 6.4,
      "ces": 0,
      "phase": "DISTRIBUTION",
      "nbp": -57.865937072503414,
      "bpi": 0.0,
      "price_usd": 1.399e-05,
      "change_24h": -9.73,
      "volume_24h": 63190.97
    },
    {
      "symbol": "bio",
      "address": "0xd655790B0486fa681c23B955F5Ca7Cd5f5C8Cb07",
      "fhs": 4.5,
      "ces": 0,
      "phase": "DISTRIBUTION",
      "nbp": -83.33333333333334,
      "bpi": 0.01574475780412995,
      "price_usd": 1.865e-06,
      "change_24h": -1.18,
      "volume_24h": 53.66
    },
    {
      "symbol": "JUNO",
      "address": "0x4E6c9f48f73E54EE5F3AB7e2992B2d733D0d0b07",
      "fhs": 6.2,
      "ces": 0,
      "phase": "DISTRIBUTION",
      "nbp": -44.97907949790795,
      "bpi": 0.0,
      "price_usd": 9.59e-06,
      "change_24h": -19.28,
      "volume_24h": 145003.39
    },
    {
      "symbol": "CLAWD",
      "address": "0x9f86dB9fc6f7c9408e8Fda3Ff8ce4e78ac7a6b07",
      "fhs": 5.9,
      "ces": 0,
      "phase": "DISTRIBUTION",
      "nbp": -56.886227544910184,
      "bpi": 0.0,
      "price_usd": 3.936e-05,
      "change_24h": -3.94,
      "volume_24h": 69016.21
    },
    {
      "symbol": "Doppel",
      "address": "0xf27b8ef47842E6445E37804896f1BC5e29381b07",
      "fhs": 6.3,
      "ces": 0,
      "phase": "DISTRIBUTION",
      "nbp": -29.08366533864542,
      "bpi": 0.0,
      "price_usd": 3.987e-06,
      "change_24h": -11.24,
      "volume_24h": 44290.52
    },
    {
      "symbol": "CLANKER",
      "address": "0x1bc0c42215582d5a085795f4badbac3ff36d1bcb",
      "fhs": 5.9,
      "ces": 0,
      "phase": "ACCUMULATION",
      "nbp": 61.29032258064516,
      "bpi": 0.0,
      "price_usd": 25.96,
      "change_24h": -1.11,
      "volume_24h": 19754.24
    },
    {
      "symbol": "DRB",
      "address": "0x3ec2156d4c0a9cbdab4a016633b7bcf6a8d68ea2",
      "fhs": 6.7,
      "ces": 0,
      "phase": "CONSOLIDATION",
      "nbp": -3.6544850498338874,
      "bpi": 1.073312081553295,
      "price_usd": 7.864e-05,
      "change_24h": 12.21,
      "volume_24h": 236128.88
    },
    {
      "symbol": "Lumen",
      "address": "0xa9FEE7b2F54781A14c85A1B8815345AefbE1EB07",
      "fhs": 6.5,
      "ces": 0,
      "phase": "DISTRIBUTION",
      "nbp": -50.0,
      "bpi": 0.0,
      "price_usd": 3.934e-06,
      "change_24h": -5.55,
      "volume_24h": 4264.52
    },
    {
      "symbol": "VVV",
      "address": "0xacfe6019ed1a7dc6f7b508c02d1b04ec88cc21bf",
      "fhs": 3.3,
      "ces": 0,
      "phase": "ACCUMULATION",
      "nbp": 15.471250740960285,
      "bpi": 0.0,
      "price_usd": 6.38,
      "change_24h": -2.01,
      "volume_24h": 1698060.48
    }
  ],
  "raw_report": "# \ud83d\udd2c SENIOR ON-CHAIN FORENSIC ANALYSIS\n\n## 1. \ud83c\udfc6 TOP 3 OPPORTUNITIES\n\n**DRB** - CES: 82/100 | FHS: 6.7/10\n- Phase: CONSOLIDATION | CP: 40.7%\n- Active signals: Bull Flag Class 1, Premium FQS, RMD Positive, Stable Price\n- Bull Flag: Class 1 | BPI: 1.07 | Fib Target: $0.000094 (+19%)\n- Holders: Top5 = 19.6% | HD: -0.3% vs previous | Structure: Safe/Distributed\n- Entry zone: $0.000075 - $0.000079 | Stop loss: $0.000067 | Target: $0.000094\n- Risks: Insider Funding (FCI 66.8%), ICR 7.17 (elevated but stable).\n\n**CLANKER** - CES: 75/100 | FHS: 5.9/10\n- Phase: ACCUMULATION | CP: 50.4%\n- Active signals: SAC (Silent Accumulation), Buy Wall (DAI 0.61), NBP Buy Pressure (+61%)\n- Bull Flag: N/A | BPI: N/A | Fib Target: Internal Resistance Breakout\n- Holders: Top5 = 43.6% | HD: +3.2% vs previous | Structure: Centralized/Insider Heavy\n- Entry zone: $24.50 - $26.00 | Stop loss: $21.80 | Target: $32.00\n- Risks: Extreme ICR (20.08), 100% FCI (Pure Insider Funding).\n\n**VVV** - CES: 55/100 | FHS: 3.3/10\n- Phase: ACCUMULATION | CP: 35.2%\n- Active signals: Technical Oversold (RSI 37, BER 0.08), Buy Pressure (+15%)\n- Bull Flag: Class 0 | BPI: 0.0 | Fib Target: Mean Reversion Target $7.20\n- Holders: Top5 = 114.7% (Logic: Burn/Lock Overlap) | HD: N/A | Structure: Fragile LCR\n- Entry zone: $6.10 - $6.40 | Stop loss: $5.80 | Target: $7.20 (+12%)\n- Risks: Critical ICR (656.52), Fragile Liquidity Coverage (LCR 1.16%).\n\n---\n\n## 2. \u26a0\ufe0f TOKENS IN DISTRIBUTION / NEGATIVE MOMENTUM\n\n**JUNO** \u26a0\ufe0f NEGATIVE MOMENTUM\n- Signal: Technical Exhaustion / RSI Oversold Expansion\n- Details: NBP -45%, Price change 24h -19.28%, RSI 16.1.\n- Since: 2 consecutive cycles.\n- Recommendation: WAIT for RSI divergence; current selling pressure is too sharp to catch the knife.\n\n**CLAWD** \u26a0\ufe0f NEGATIVE MOMENTUM\n- Signal: Invalidated Bull Flag / Distribution Phase\n- Details: NBP -57%, ICR 3.38, price trending toward lower BB.\n- Since: 1 cycle (Flag lost).\n- Recommendation: EXIT IF price drops below $0.000035.\n\n---\n\n## 3. \ud83d\udc0b WHALE WATCH\n\n| Token | Top Whale | % Supply | Type | Entity | Alert |\n|-------|-----------|----------|------|--------|-------|\n| CLANKER | 0x8d4a... | 13.98% | Contract | - | \u2705 LP/Safe |\n| VVV | 0x328d... | 28.79% | Contract | - | \u2705 Locked |\n| JUNO | 0xeaec... | 5.04% | EOA | - | \u26a0\ufe0f Anonymous |\n| DRB | 0x3e2b... | 5.70% | EOA | - | \u26a0\ufe0f Anonymous buying |\n\n---\n\n## 4. \ud83d\udcca SUMMARY TABLE\n\n| Token | Phase | FHS | NBP | BPI | SI | ICR | Top5% | CES | Signal |\n|-------|-------|-----|-----|-----|-----|-----|-------|-----|--------|\n| DRB | CONSO | 6.7 | -4% | 1.07| 0.6%| 7.17| 19.6% | 82 | \ud83d\udfe2 BF Premium |\n| CLANKER | ACCUM | 5.9 | +61%| 0.0 | 0.0%| 20.0| 43.6% | 75 | \ud83d\udfe2 SAC+Buy Wall |\n| VVV | ACCUM | 3.3 | +15%| 0.0 | 0.0%| 656 | 114%* | 55 | \ud83d\udfe1 Oversold |\n| FELIX | DIST | 6.4 | -58%| 0.0 | 12% | 2.41| 27.0% | 42 | \u26aa Watch |\n| JUNO | DIST | 6.2 | -45%| 0.0 | 0.0%| 2.62| 29.6% | 35 | \u26aa Watch |\n\n*Note: VVV Top5% > 100% indicates multiple large contracts/burn addresses being counted in calculation logic.*\n\n---\n\n## 5. \ud83d\udd04 CHANGES VS PREVIOUS\n\n1. \ud83d\udc8e **SAC (Silent Accumulation)**: Detected in **CLANKER**. Price stable (-1.11%) while NBP flipped to +61%. Solid buy wall (DAI 0.61).\n2. \u26a0\ufe0f **Flag Invalidation**: **CLAWD** and **CLANKER** have both officially lost their bull flag structures this cycle.\n3. \ud83c\udf0a **VPD Absorption**: **DRB** is showing high volume ($236k) with minimal price volatility, indicating smart money is absorbing the 12% gain without nuking the bid.\n4. \ud83d\udea9 **New Bull Flags**: **BUNKER** (Class 1) and **bio** (Class 1) detected, though both have low BPI (Improbable) due to current sell walls.\n\n---\n\n## 6. \ud83c\udfaf ACTION PLAN\n\n\ud83d\udccc **RECOMMENDED ENTRIES (CES \u2265 50):**\n- **DRB**: CES=82 | Entry $0.000078, Stop $0.000067, Target $0.000094 (R:R = 1.4:1). *Strongest technical setup.*\n- **CLANKER**: CES=75 | Entry $25.96, Stop $21.80, Target $32.00 (R:R = 1.45:1). *Accumulation play.*\n\n\ud83d\udc40 **WATCHLIST (CES 30-49, await confirmation):**\n- **JUNO**: Wait for RSI 1h to cross 30. Missing signal: RSI reversal.\n- **BUNKER**: Wait for NBP to flip positive (>15%). Missing signal: Buyer pressure.\n\n\ud83d\udeaa **RECOMMENDED EXITS:**\n- **CLAWD**: Exit now if holding; the loss of the Bull Flag combined with high distribution (-57%) suggests further downside.\n\nReport generated: 2026-03-26T04:42:27Z\nAnalyzed: 2026-03-26 04:50:00\nTokens: 13\nTotal alerts: 26\nTop CES: DRB = 82/100\n\n\ud83d\udd10 **SEALED ONBASE**: 0x25fc6cf3404ceb7b... (TX: Pending)",
  "seal": {
    "report_hash": "25fc6cf3404ceb7b5413f2c6cbe033bfc1b68d496df9f4bf7288241028a37246",
    "tx_hash": null
  },
  "active_signals": [
    {
      "symbol": "AntiHunter",
      "type": "BULL_FLAG",
      "status": "HOLDING",
      "since": "previous_cycle",
      "note": "Bull flag still active"
    },
    {
      "symbol": "BNKRW",
      "type": "BULL_FLAG",
      "status": "HOLDING",
      "since": "previous_cycle",
      "note": "Bull flag remains active"
    },
    {
      "symbol": "BUNKER",
      "type": "BULL_FLAG",
      "status": "HOLDING",
      "since": "previous_cycle",
      "note": "Bull flag still active"
    },
    {
      "symbol": "bio",
      "type": "BULL_FLAG",
      "status": "HOLDING",
      "since": "previous_cycle",
      "note": "Bull flag remains active"
    },
    {
      "symbol": "DRB",
      "type": "BULL_FLAG",
      "status": "HOLDING",
      "since": "previous_cycle",
      "note": "Bull flag still active"
    }
  ],
  "signal_evolution": "### 1. MARKET OVERVIEW\nThe overall market is currently in a mixed state, with most tokens in the distribution phase, but some showing signs of accumulation or consolidation. Notable shifts include CLANKER's significant increase in FHS and NBP, indicating potential accumulation, and CLAWD's loss of its bull flag.\n\n### 2. PRICE & VOLUME HIGHLIGHTS\nNo significant price or volume movements were observed in the given data, as all tokens had a price delta of 0% and a volume delta of 0%. However, some "
}