{
  "updated_at": "2026-04-04T08:43:32.086720+00:00",
  "synthesis_table": [
    {
      "symbol": "MOLT",
      "address": "0xB695559b26BB2c9703ef1935c37AeaE9526bab07",
      "fhs": 7.2,
      "ces": 0,
      "phase": "DISTRIBUTION",
      "nbp": -53.125,
      "bpi": 0.0,
      "price_usd": 1.62e-05,
      "change_24h": -6.93,
      "volume_24h": 13307.1
    },
    {
      "symbol": "AntiHunter",
      "address": "0xe2f3FaE4bc62E21826018364aa30ae45D430bb07",
      "fhs": 6.4,
      "ces": 0,
      "phase": "DISTRIBUTION",
      "nbp": -53.125,
      "bpi": 0.017496104221129297,
      "price_usd": 2.274e-06,
      "change_24h": 1.57,
      "volume_24h": 6235.91
    },
    {
      "symbol": "CLAWNCH",
      "address": "0xa1F72459dfA10BAD200Ac160eCd78C6b77a747be",
      "fhs": 6.5,
      "ces": 0,
      "phase": "DISTRIBUTION",
      "nbp": -62.882096069869,
      "bpi": 0.0,
      "price_usd": 2.647e-05,
      "change_24h": -4.04,
      "volume_24h": 14244.4
    },
    {
      "symbol": "BNKRW",
      "address": "0xf48bC234855aB08ab2EC0cfaaEb2A80D065a3b07",
      "fhs": 6.8,
      "ces": 0,
      "phase": "DISTRIBUTION",
      "nbp": -50.0,
      "bpi": 2.49200148751488,
      "price_usd": 2.436e-06,
      "change_24h": -0.28,
      "volume_24h": 692.27
    },
    {
      "symbol": "fomolt",
      "address": "0xeff5672a3e73e104A56b7d16c1166f2Ae0714b07",
      "fhs": 5.9,
      "ces": 0,
      "phase": "DISTRIBUTION",
      "nbp": -100.0,
      "bpi": 0.0,
      "price_usd": 1.832e-06,
      "change_24h": -1.71,
      "volume_24h": 485.86
    },
    {
      "symbol": "WORK",
      "address": "0xe6725BE5AC8DFf03538a9ef3E3a7A6BEd256bB4f",
      "fhs": 6.0,
      "ces": 0,
      "phase": "DISTRIBUTION",
      "nbp": -100.0,
      "bpi": 0.0,
      "price_usd": 0.0002289,
      "change_24h": -10.67,
      "volume_24h": 1556.51
    },
    {
      "symbol": "UNKNOWN",
      "address": "0x2A767b649A4c469f2c4F88f85D4eFb6be7abFB07",
      "fhs": 5.4,
      "ces": 0,
      "phase": "CONSOLIDATION",
      "nbp": 0.0,
      "bpi": 0.0,
      "price_usd": 0.0,
      "change_24h": 0.0,
      "volume_24h": 0.0
    },
    {
      "symbol": "BUNKER",
      "address": "0xCe16Ef461d88256D2D80DFD31F0D9E7a9fD59213",
      "fhs": 6.3,
      "ces": 0,
      "phase": "DISTRIBUTION",
      "nbp": -100.0,
      "bpi": 1.4324474512745313,
      "price_usd": 7.952e-07,
      "change_24h": -1.99,
      "volume_24h": 444.95
    },
    {
      "symbol": "FELIX",
      "address": "0xf30Bf00edd0C22db54C9274B90D2A4C21FC09b07",
      "fhs": 5.5,
      "ces": 0,
      "phase": "DISTRIBUTION",
      "nbp": -58.51393188854489,
      "bpi": 0.0021938724126806773,
      "price_usd": 6.998e-06,
      "change_24h": 0.59,
      "volume_24h": 56619.54
    },
    {
      "symbol": "bio",
      "address": "0xd655790B0486fa681c23B955F5Ca7Cd5f5C8Cb07",
      "fhs": 5.6,
      "ces": 0,
      "phase": "DISTRIBUTION",
      "nbp": -66.66666666666666,
      "bpi": 0.08231267553697547,
      "price_usd": 1.631e-06,
      "change_24h": -0.54,
      "volume_24h": 5.77
    },
    {
      "symbol": "JUNO",
      "address": "0x4E6c9f48f73E54EE5F3AB7e2992B2d733D0d0b07",
      "fhs": 4.8,
      "ces": 0,
      "phase": "DISTRIBUTION",
      "nbp": -63.287671232876704,
      "bpi": 0.0005936838789119901,
      "price_usd": 6.823e-06,
      "change_24h": 7.98,
      "volume_24h": 21887.09
    },
    {
      "symbol": "CLAWD",
      "address": "0x9f86dB9fc6f7c9408e8Fda3Ff8ce4e78ac7a6b07",
      "fhs": 6.0,
      "ces": 0,
      "phase": "DISTRIBUTION",
      "nbp": -54.91329479768786,
      "bpi": 0.0,
      "price_usd": 2.475e-05,
      "change_24h": -1.68,
      "volume_24h": 15584.98
    },
    {
      "symbol": "Doppel",
      "address": "0xf27b8ef47842E6445E37804896f1BC5e29381b07",
      "fhs": 6.4,
      "ces": 0,
      "phase": "DISTRIBUTION",
      "nbp": -44.329896907216494,
      "bpi": 0.0,
      "price_usd": 3.649e-06,
      "change_24h": -4.79,
      "volume_24h": 27630.27
    },
    {
      "symbol": "CLANKER",
      "address": "0x1bc0c42215582d5a085795f4badbac3ff36d1bcb",
      "fhs": 5.0,
      "ces": 0,
      "phase": "ACCUMULATION",
      "nbp": 20.689655172413794,
      "bpi": 0.14230086232720315,
      "price_usd": 25.052,
      "change_24h": -0.19,
      "volume_24h": 2228.41
    },
    {
      "symbol": "DRB",
      "address": "0x3ec2156d4c0a9cbdab4a016633b7bcf6a8d68ea2",
      "fhs": 4.9,
      "ces": 0,
      "phase": "CONSOLIDATION",
      "nbp": -3.7735849056603774,
      "bpi": 0.0001776269967598015,
      "price_usd": 0.0001049,
      "change_24h": 10.73,
      "volume_24h": 193780.6
    },
    {
      "symbol": "Lumen",
      "address": "0xa9FEE7b2F54781A14c85A1B8815345AefbE1EB07",
      "fhs": 5.2,
      "ces": 0,
      "phase": "DISTRIBUTION",
      "nbp": -15.723270440251572,
      "bpi": 0.19534100506525467,
      "price_usd": 3.359e-06,
      "change_24h": 13.12,
      "volume_24h": 25793.2
    },
    {
      "symbol": "VVV",
      "address": "0xacfe6019ed1a7dc6f7b508c02d1b04ec88cc21bf",
      "fhs": 3.7,
      "ces": 0,
      "phase": "CONSOLIDATION",
      "nbp": 0.5732152162584679,
      "bpi": 0.0,
      "price_usd": 6.95,
      "change_24h": -2.03,
      "volume_24h": 657116.09
    }
  ],
  "raw_report": "# \ud83d\udd2c SENIOR ON-CHAIN FORENSIC ANALYSIS\n\n## 1. \ud83c\udfc6 TOP 3 OPPORTUNITIES\n\n**BNKRW** - CES: 54/100 | FHS: 6.8/10\n- Phase: DISTRIBUTION | CP: 34.3%\n- Active signals: Bull Flag Convergence, LVR Momentum +\n- Bull Flag: Class 2 | BPI: 2.49 (Breakout probable) | Fib Target: $0.000003 (+7.2%)\n- Holders: Top5 = 67.6% | HD: [Stable vs memory] | Structure [Concentrated]\n- Entry zone: $0.0000023 - $0.0000024 | Stop loss: $0.0000022 | Target: $0.000003\n- Risks: High ICR (3.38), Centralized Supply (67.6%). Breaking through distribution phase is mandatory.\n\n**CLANKER** - CES: 50/100 | FHS: 5.0/10\n- Phase: ACCUMULATION | CP: 13%\n- Active signals: SAC (Silent Accumulation - NBP +21%), Phase Change\n- Bull Flag: Class 3 | BPI: 0.14 | Fib Target: $25.83 (+3%)\n- Holders: Top5 = 44.3% | HD: [Positive accumulation pattern] | Structure [Insider heavy]\n- Entry zone: $24.70 - $25.05 | Stop loss: $24.00 | Target: $26.50\n- Risks: Extreme ICR (20.86), High FCI (100%), Insider Funding.\n\n**AntiHunter** - CES: 42/100 | FHS: 6.4/10\n- Phase: DISTRIBUTION | CP: 8.7%\n- Active signals: Bull Flag Convergence (Class 2)\n- Bull Flag: Class 2 | BPI: 0.02 | Fib Target: $0.00000247 (+9%)\n- Holders: Top5 = 42.8% | HD: [Neutral] | Structure [Centralized]\n- Entry zone: $0.00000217 - $0.00000225 | Stop loss: $0.00000210 | Target: $0.00000247\n- Risks: Fragile FQS (57), Neutral momentum in distribution.\n\n---\n\n## 2. \u26a0\ufe0f TOKENS IN DISTRIBUTION / NEGATIVE MOMENTUM\n\n**WORK** \u26a0\ufe0f NEGATIVE MOMENTUM\n- Signal: Distribution / Extreme ICR\n- Details: NBP -100%, ICR 13.09, Top5% concentration 81.2%.\n- Since: Persistently in distribution phase.\n- Recommendation: EXIT. ICR > 10 is a blocking filter.\n\n**VVV** \u26a0\ufe0f NEGATIVE MOMENTUM\n- Signal: Critical FHS / Structural Risk\n- Details: FHS 3.7/10, ICR 639.39 (Critical concentration), Top 5 holds >100% of supply (centralized anomaly).\n- Since: Current cycle.\n- Recommendation: EXIT. Market illusion due to extreme concentration.\n\n---\n\n## 3. \ud83d\udc0b WHALE WATCH\n\n| Token | Top Whale | % Supply | Type | Entity | Alert |\n|-------|-----------|----------|------|--------|-------|\n| MOLT | 0xfc72... | 6.93% | EOA | Anonymous | \u26a0\ufe0f Active distribution |\n| BNKRW | 0xba5e... | 26.24% | Contract| - | \u2705 Significant position |\n| CLANKER| 0x8d4a... | 14.04% | Contract| - | \ud83d\udc8e Syndicate Source |\n| JUNO | 0xeaec... | 6.11% | EOA | Anonymous | \u26a0\ufe0f High FCI (77.4%) |\n\n---\n\n## 4. \ud83d\udcca SUMMARY TABLE\n\n| Token | Phase | FHS | NBP | BPI | SI | ICR | Top5% | CES | Signal |\n|-------|-------|-----|-----|-----|-----|-----|-------|-----|--------|\n| BNKRW | DIST | 6.8 | -50%| 2.49| 0.7%| 3.38| 67.6% | 54 | \ud83d\udfe1 BF+CP |\n| CLANKER| ACCUM | 5.0 | +21%| 0.14| 4.1%| 20.8| 44.3% | 50 | \ud83d\udfe1 SAC+PC |\n| MOLT | DIST | 7.2 | -53%| 0.00| 0.0%| 1.45| 27.1% | 25 | \ud83d\udd34 DIST |\n| AntiH | DIST | 6.4 | -53%| 0.02| 0.0%| 1.27| 42.8% | 42 | \u26aa WATCH |\n| CLAWNCH| DIST | 6.5 | -63%| 0.00| 21.5| 2.29| 21.1% | 15 | \ud83d\udd34 LOST BF|\n| DRB | CONSOL| 4.9 | -4% | 0.00| 0.3%| 8.45| 18.5% | 35 | \u26aa WATCH |\n\nLegend: \ud83d\udfe2 = CES \u2265 70 | \ud83d\udfe1 = CES 50-69 | \ud83d\udd34 = CES < 30\n\n---\n\n## 5. \ud83d\udd04 CHANGES VS PREVIOUS\n\n1. \ud83d\udd04 **Phase Changes**:\n   - **CLANKER**: Transitioned from Distribution to **ACCUMULATION**. NBP flipped to +21%.\n2. \ud83d\udc8e **SAC (Silent Accumulation)**:\n   - **CLANKER**: Detected based on phase shift and positive NBP despite low BPI.\n3. \ud83d\udea9 **Lost/Invalidated Flags**:\n   - **CLAWNCH**: Bull flag invalidated this cycle. CES dropped significantly.\n4. \ud83d\udc0b **Holder Drift**:\n   - **JUNO**: Whale Syndicate coordination (WCC 21.5) remains high with high FCI (77.4%).\n\n---\n\n## 6. \ud83c\udfaf ACTION PLAN\n\n\ud83d\udccc **RECOMMENDED ENTRIES (CES \u2265 50):**\n- **BNKRW**: CES=54 | Entry $0.00000244, Stop $0.00000220, Target $0.000003 (R:R = 2.3:1). Confirm if NBP improves next cycle.\n- **CLANKER**: CES=50 | Entry $25.05, Stop $24.00, Target $26.50 (R:R = 1.4:1). Small size due to high ICR.\n\n\ud83d\udc40 **WATCHLIST (CES 30-49):**\n- **DRB**: Wait for phase shift to Accumulation. Currently in consolidation with neutral NBP.\n- **AntiHunter**: Bull flag active but BPI is extremely low (Improbable). Wait for volume to confirm expansion.\n\n\ud83d\udeaa **RECOMMENDED EXITS:**\n- **WORK**: ICR (13.09) exceeds safety filters. Exit position.\n- **VVV**: Structural risk (ICR 639.39) is absolute. Market concentration makes movements artificial.\n\n\u26d4 **BLACKLIST:**\n- **VVV**: Extreme concentration prevents organic price discovery.\n\n```\nReport generated: 2026-04-04T08:00:02.892429\nAnalyzed: 2026-04-04T08:55:00\nTokens: 14\nTotal alerts: 32\nTop CES: BNKRW = 54/100\n```\n\n\ud83d\udd10 **SEALED ONBASE**: 0x2d6d68bd604612f7... (TX: Pending)",
  "seal": {
    "report_hash": "2d6d68bd604612f7345a1d04047c708318f34d6af9e5c21cfdbd64e5f1c6f092",
    "tx_hash": null
  },
  "active_signals": [
    {
      "symbol": "AntiHunter",
      "type": "BULL_FLAG",
      "status": "CONFIRMED",
      "since": "previous_cycle",
      "note": "Remains active with minor changes"
    },
    {
      "symbol": "BNKRW",
      "type": "BULL_FLAG",
      "status": "HOLDING",
      "since": "previous_cycle",
      "note": "No significant changes"
    },
    {
      "symbol": "CLAWNCH",
      "type": "BULL_FLAG",
      "status": "INVALIDATED",
      "since": "current_cycle",
      "note": "Lost bull flag"
    },
    {
      "symbol": "BUNKER",
      "type": "BULL_FLAG",
      "status": "CONFIRMED",
      "since": "previous_cycle",
      "note": "Remains active"
    },
    {
      "symbol": "FELIX",
      "type": "BULL_FLAG",
      "status": "HOLDING",
      "since": "previous_cycle",
      "note": "Minor changes"
    },
    {
      "symbol": "bio",
      "type": "BULL_FLAG",
      "status": "HOLDING",
      "since": "previous_cycle",
      "note": "No significant changes"
    },
    {
      "symbol": "JUNO",
      "type": "BULL_FLAG",
      "status": "HOLDING",
      "since": "previous_cycle",
      "note": "Minor changes"
    },
    {
      "symbol": "CLAWD",
      "type": "BULL_FLAG",
      "status": "HOLDING",
      "since": "previous_cycle",
      "note": "Minor changes"
    },
    {
      "symbol": "Doppel",
      "type": "BULL_FLAG",
      "status": "HOLDING",
      "since": "previous_cycle",
      "note": "Minor changes"
    },
    {
      "symbol": "Lumen",
      "type": "BULL_FLAG",
      "status": "HOLDING",
      "since": "previous_cycle",
      "note": "Minor changes"
    },
    {
      "symbol": "DRB",
      "type": "BULL_FLAG",
      "status": "HOLDING",
      "since": "previous_cycle",
      "note": "Minor changes"
    },
    {
      "symbol": "CLANKER",
      "type": "PHASE_CHANGE",
      "status": "DETECTED",
      "since": "current_cycle",
      "note": "Transitioned to accumulation phase"
    }
  ],
  "signal_evolution": "### 1. MARKET OVERVIEW\nThe overall market is currently in a mixed state, with most tokens in the distribution phase, but some showing signs of accumulation or consolidation. Notable shifts include CLANKER's phase change from distribution to accumulation and the loss of a bull flag by CLAWNCH.\n\n### 2. PRICE & VOLUME HIGHLIGHTS\nThere are no significant price or volume movements greater than 2% or 20% respectively for any token in the provided data. However, it's worth noting that several tokens ha"
}